asyncpg_opentracing/__init__.py
asyncpg_opentracing/tracing.py
asyncpg_opentracing-0.1.0.dist-info/LICENSE.md
asyncpg_opentracing-0.1.0.dist-info/METADATA
asyncpg_opentracing-0.1.0.dist-info/WHEEL
asyncpg_opentracing-0.1.0.dist-info/top_level.txt
asyncpg_opentracing-0.1.0.dist-info/RECORD
