Metadata-Version: 2.1
Name: asyncpg-opentracing
Version: 0.1.0
Summary: Opentracing instrumentation for asyncpg
Home-page: https://github.com/condorcet/asyncpg-opentracing
Author: Vasilii Novikov
Author-email: novikov.vz@gmail.com
License: MIT
Keywords: opentracing
Platform: any
Classifier: Development Status :: 3 - Alpha
Classifier: Intended Audience :: Developers
Classifier: License :: OSI Approved :: MIT License
Classifier: Operating System :: OS Independent
Classifier: Programming Language :: Python
Classifier: Programming Language :: Python :: 3.6
Classifier: Programming Language :: Python :: 3.7
Classifier: Topic :: Software Development :: Libraries :: Python Modules
Requires-Python: >=3.6
Requires-Dist: asyncpg (>=0.17)
Requires-Dist: opentracing (<3,>2)
